xdutools/__init__.py
xdutools/apps/__init__.py
xdutools/apps/grade.py
xdutools/apps/schedule.py
xdutools/auth/__init__.py
xdutools/auth/cookies.py
xdutools/auth/ehall.py
xdutools/auth/ids.py
xdutools/auth/nic.py
xdutools/auth/types.py
xdutools/auth/utils.py
xdutools/cli.py
xdutools/state.py
xdutools/utils.py
xdutools-0.0.1a3.dist-info/entry_points.txt
xdutools-0.0.1a3.dist-info/LICENSE
xdutools-0.0.1a3.dist-info/WHEEL
xdutools-0.0.1a3.dist-info/METADATA
xdutools-0.0.1a3.dist-info/RECORD
